MANIFEST.in
README.md
setup.cfg
setup.py
autoreloader/__init__.py
autoreloader/admin.py
autoreloader/apps.py
autoreloader/conf.py
autoreloader/models.py
autoreloader/tests.py
autoreloader/views.py
autoreloader/management/__init__.py
autoreloader/management/commands/__init__.py
autoreloader/management/commands/autoreload.py
autoreloader/migrations/__init__.py
autoreloader/templates/autoreloader/$autoreload.js
autoreloader/templatetags/__init__.py
autoreloader/templatetags/autoreload_tags.py
django_autoreloader.egg-info/PKG-INFO
django_autoreloader.egg-info/SOURCES.txt
django_autoreloader.egg-info/dependency_links.txt
django_autoreloader.egg-info/not-zip-safe
django_autoreloader.egg-info/requires.txt
django_autoreloader.egg-info/top_level.txt